{"name": "control_structures_solution", "extension": ".py", "course": "PDS", "st_mode": 33204, "st_ino": 13100595, "st_dev": 16777233, "st_nlink": 1, "st_uid": 501, "st_gid": 20, "st_size": 2924, "st_atime": 1759510075.4115713, "st_mtime": 1759494116.0, "st_ctime": 1759510073.5258472, "st_birthtime": 1759494116.0, "st_blocks": 8, "st_blksize": 4096, "content": "'''\nExercises regarding control structures.\nThe following exercises should be solved with loops, match case and\nif-else conditions ONLY! Comprehensions are NOT part of this exercise.\n\nAuthor: RCH\nDate: 25.11.2024\n'''\n\nimport random as rd\nfrom operator import length_hint\n\n# given is the following list numbers\nnlh = rd.randrange(1,100)\nrnd = rd.choices(range(1,100), k=nlh) + rd.choices(range(100,255), k=255-nlh) + [rd.randrange(256,300)]\nrd.shuffle(rnd)\nnumbers = rnd.copy()\n\n# advanced: do all exercises with the 2d list numbers_ii\nnumbers_ii = [[rnd.pop() for _ in range(16)] for _ in range(16)]\n\n# Exercise 1:\n'''\nfind the largest number in numbers with for loops and remove it,\nif it is at the last position. Do the remove in the else clause of the for loop. WHY???\n'''\nfor i in numbers[:-1]:\n    if i == max(numbers):\n        break\nelse:\n    numbers.pop()\n\n# advanced:\nfor l in numbers_ii:\n    for ll in l[:-1]:\n        if ll == max(l):\n            break\n    else:\n        if l == numbers_ii[-1]:\n            ll.pop()\n\n\n# Exercise 2:\n'''replace all values <100 with 0.'''\nfor i in range(len(numbers)):\n    if numbers[i] < 100:\n        numbers[i] = 0\n\n# advanced:\nfor i in range(len(numbers_ii)):\n    for j in range(len(numbers_ii[i])):\n        if numbers_ii[i][j] < 100:\n            numbers_ii[i][j] = 0\n\n\n# Exercise 3:\n'''find the position of the largest number.'''\nfor i, j in enumerate(numbers):\n    if j == max(numbers):\n        break\n\n# alternative solution:\nn = 0\ni = 0\nfor l in range(len(numbers)):\n    if numbers[l] >n:\n        i = l\n        n = numbers[l]\n\n# advanced:\nmax_i = 0\nmax_j = 0\nmax_n = 0\nfor i, l in enumerate(numbers_ii):\n    for j, ll in enumerate(l):\n        if ll >max_n:\n            max_i, max_j = i, j\n\n\n# Exercise 4:\n'''write all numbers != 0 up to the position of the largest number into a new list.'''\nk = 0\nnew_numbers = []\nwhile k <= i:\n    if numbers[k] != 0:\n        new_numbers.append(numbers[k])\n    k += 1\n\n# advanced:\nnew_numbers_ii = []\nfor i in range(max_i + 1):\n    for j in range(max_j + 1):\n        if numbers_ii[i][j] != 0:\n            new_numbers_ii += [numbers_ii[i][j]]\n\n\n# Exercise 5:\n'''\ncount the number of remaining numbers for each decade with match-case statement.\nThat means, count the number of numbers in ranges:\n100 - 125, 126 - 150, 151 - 175, 176 - 200, >200 \nNote: same solution for the simple and the advanced exercises.\n'''\nc1 = c2 = c3 = c4 = c5 = 0\n\nfor i in new_numbers:\n    if i >= 100:        # not necessary since all values <100 were replaced by 0\n        match i:\n            case i if i <= 125:\n                c1 += 1\n            case i if i <= 150:\n                c2 += 1\n            case i if i <= 175:\n                c3 += 1\n            case i if i <= 200:\n                c4 += 1\n            case _:\n                c5 += 1\n\nprint(f'{c1=}, {c2=}, {c3=}, {c4=}, {c5=}')\n\nprint(f'{len(new_numbers)=}')\nprint(f'{sum([c1, c2, c3, c4, c5])=}')\n\n"}